security_lake_tools/__init__.py
security_lake_tools/cli.py
security_lake_tools/create_source.py
security_lake_tools-1.0.0.dist-info/METADATA
security_lake_tools-1.0.0.dist-info/WHEEL
security_lake_tools-1.0.0.dist-info/entry_points.txt
security_lake_tools-1.0.0.dist-info/licenses/LICENSE
security_lake_tools-1.0.0.dist-info/RECORD
