Metadata-Version: 2.4
Name: security-lake-tools
Version: 1.0.0
Summary: Tools for managing AWS Security Lake custom sources
Project-URL: Homepage, https://github.com/tenzir/security-lake-tools
Project-URL: Repository, https://github.com/tenzir/security-lake-tools
Project-URL: Issues, https://github.com/tenzir/security-lake-tools/issues
Project-URL: Documentation, https://github.com/tenzir/security-lake-tools#readme
Author-email: Tenzir <engineering@tenzir.com>
License: Apache-2.0
License-File: LICENSE
Keywords: aws,logging,ocsf,security,security-lake
Classifier: Development Status :: 4 - Beta
Classifier: Intended Audience :: Developers
Classifier: Intended Audience :: System Administrators
Classifier: License :: OSI Approved :: Apache Software License
Classifier: Programming Language :: Python :: 3
Classifier: Programming Language :: Python :: 3.12
Classifier: Programming Language :: Python :: 3.13
Classifier: Topic :: Security
Classifier: Topic :: System :: Logging
Requires-Python: >=3.12
Requires-Dist: boto3>=1.26.0
Requires-Dist: botocore>=1.29.0
Provides-Extra: dev
Requires-Dist: black>=23.0; extra == 'dev'
Requires-Dist: boto3-stubs[iam,securitylake,sts]>=1.26.0; extra == 'dev'
Requires-Dist: mypy>=1.0; extra == 'dev'
Requires-Dist: pytest-cov>=4.0; extra == 'dev'
Requires-Dist: pytest>=7.0; extra == 'dev'
Requires-Dist: ruff>=0.1.0; extra == 'dev'
